{
  "protocol_version" : "0.0.4",
  "configuration" : {
    "version" : "(5.20.1.19) (tarball)",
    "tlc" : "__thread",
    "sigsgev" : "altstack",
    "notifications" : "epoll",
    "architecture" : "amd64",
    "disabled_features" : "none",
    "smallconfig" : "disabled",
    "bigarrays" : "disabled",
    "softdebug" : "enabled",
    "interpreter" : "enabled",
    "suspend" : "hybrid",
    "llvm_support" : "600"
  },
  "memory" : {
    "minor_gc_time" : "50929100",
    "major_gc_time" : "178258",
    "minor_gc_count" : "20733",
    "major_gc_count" : "22",
    "major_gc_time_concurrent" : "32825969"
 },
  "threads" : [
 {
    "is_managed" : true,
    "offset_free_hash" : "0x400e11064",
    "offset_rich_hash" : "0x400e111ee",
    "crashed" : true,
    "native_thread_id" : "0x7f021d5d7780",
    "thread_info_addr" : "0x55d22bd875d0",
    "thread_name" : "mono",
    "ctx" : {
      "IP" : "0x7f021d61fed7",
      "SP" : "0x7ffd1b6b77a0",
      "BP" : "0x4"
  },
    "managed_frames" : [
  {
      "native_address" : "unregistered"
   }
,
  {
      "is_managed" : "true",
      "guid" : "6649516E-5B35-4231-9FB2-62B421AF0ADB",
      "token" : "0x00000",
      "native_offset" : "0x0",
      "filename" : "mscorlib.dll",
      "sizeofimage" : "0x450000",
      "timestamp" : "0xa2bd1ab9",
      "il_offset" : "0x0000b"
   }
,
  {
      "is_managed" : "true",
      "guid" : "6649516E-5B35-4231-9FB2-62B421AF0ADB",
      "token" : "0x6004841",
      "native_offset" : "0x0",
      "filename" : "mscorlib.dll",
      "sizeofimage" : "0x450000",
      "timestamp" : "0xa2bd1ab9",
      "il_offset" : "0x00000"
   }
,
  {
      "is_managed" : "true",
      "guid" : "6649516E-5B35-4231-9FB2-62B421AF0ADB",
      "token" : "0x6001968",
      "native_offset" : "0x0",
      "filename" : "mscorlib.dll",
      "sizeofimage" : "0x450000",
      "timestamp" : "0xa2bd1ab9",
      "il_offset" : "0x00008"
   }
,
  {
      "is_managed" : "true",
      "guid" : "6649516E-5B35-4231-9FB2-62B421AF0ADB",
      "token" : "0x60018c8",
      "native_offset" : "0x0",
      "filename" : "mscorlib.dll",
      "sizeofimage" : "0x450000",
      "timestamp" : "0xa2bd1ab9",
      "il_offset" : "0x00000"
   }
,
  {
      "is_managed" : "true",
      "guid" : "ED39F21B-9E93-43DC-BD44-2A17AD356A9F",
      "token" : "0x6000260",
      "native_offset" : "0x0",
      "filename" : "glib-sharp.dll",
      "sizeofimage" : "0x1e000",
      "timestamp" : "0x0",
      "il_offset" : "0x0007d"
   }
,
  {
      "is_managed" : "true",
      "guid" : "ED39F21B-9E93-43DC-BD44-2A17AD356A9F",
      "token" : "0x60002aa",
      "native_offset" : "0x0",
      "filename" : "glib-sharp.dll",
      "sizeofimage" : "0x1e000",
      "timestamp" : "0x0",
      "il_offset" : "0x0000c"
   }
,
  {
      "is_managed" : "true",
      "guid" : "ED39F21B-9E93-43DC-BD44-2A17AD356A9F",
      "token" : "0x60002ac",
      "native_offset" : "0x0",
      "filename" : "glib-sharp.dll",
      "sizeofimage" : "0x1e000",
      "timestamp" : "0x0",
      "il_offset" : "0x000b1"
   }
,
  {
      "is_managed" : "true",
      "guid" : "ED39F21B-9E93-43DC-BD44-2A17AD356A9F",
      "token" : "0x00000",
      "native_offset" : "0x0",
      "filename" : "glib-sharp.dll",
      "sizeofimage" : "0x1e000",
      "timestamp" : "0x0",
      "il_offset" : "0xffffffff"
   }
,
  {
      "native_address" : "unregistered"
   }
,
  {
      "is_managed" : "true",
      "guid" : "7AAB76E8-7BCE-48A4-B45C-F7FA613CB70C",
      "token" : "0x00000",
      "native_offset" : "0x0",
      "filename" : "gtk-sharp.dll",
      "sizeofimage" : "0x164000",
      "timestamp" : "0x0",
      "il_offset" : "0x0000c"
   }
,
  {
      "is_managed" : "true",
      "guid" : "7AAB76E8-7BCE-48A4-B45C-F7FA613CB70C",
      "token" : "0x60041c1",
      "native_offset" : "0x0",
      "filename" : "gtk-sharp.dll",
      "sizeofimage" : "0x164000",
      "timestamp" : "0x0",
      "il_offset" : "0x00000"
   }
,
  {
      "is_managed" : "true",
      "guid" : "7BB62E53-530F-48D5-9590-F3BFFAC96041",
      "token" : "0x6000022",
      "native_offset" : "0x0",
      "filename" : "reserve",
      "sizeofimage" : "0xe000",
      "timestamp" : "0x5d5169f2",
      "il_offset" : "0x00014"
   }
,
  {
      "is_managed" : "true",
      "guid" : "7BB62E53-530F-48D5-9590-F3BFFAC96041",
      "token" : "0x6000021",
      "native_offset" : "0x0",
      "filename" : "reserve",
      "sizeofimage" : "0xe000",
      "timestamp" : "0x5d5169f2",
      "il_offset" : "0x00000"
   }
,
  {
      "is_managed" : "true",
      "guid" : "6649516E-5B35-4231-9FB2-62B421AF0ADB",
      "token" : "0x00000",
      "native_offset" : "0x0",
      "filename" : "mscorlib.dll",
      "sizeofimage" : "0x450000",
      "timestamp" : "0xa2bd1ab9",
      "il_offset" : "0x0001e"
   }

  ],
  "unmanaged_frames" : [
 {
    "native_address" : "unregistered"
  }
,
 {
    "native_address" : "unregistered"
  }
,
 {
    "native_address" : "unregistered"
  }
,
 {
    "native_address" : "unregistered"
  }
,
 {
    "native_address" : "unregistered"
  }
,
 {
    "native_address" : "unregistered"
  }
,
 {
    "native_address" : "unregistered"
  }
,
 {
    "native_address" : "unregistered"
  }
,
 {
    "native_address" : "unregistered"
  }
,
 {
    "native_address" : "unregistered"
  }
,
 {
    "native_address" : "unregistered"
  }
,
 {
    "native_address" : "unregistered"
  }
,
 {
    "native_address" : "unregistered"
  }
,
 {
    "native_address" : "unregistered"
  }
,
 {
    "native_address" : "unregistered"
  }
,
 {
    "native_address" : "unregistered"
  }
,
 {
    "native_address" : "unregistered"
  }
,
 {
    "native_address" : "unregistered"
  }

 ]
},
{
  "is_managed" : true,
  "offset_free_hash" : "0x381c712c1",
  "offset_rich_hash" : "0x381c714ac",
  "crashed" : false,
  "native_thread_id" : "0x7f02126ab700",
  "thread_info_addr" : "0x7f02040037d0",
  "thread_name" : "mono",
  "ctx" : {
    "IP" : "0x7f021d7f0916",
    "SP" : "0x7f02126aa6a0",
    "BP" : "0x55d22b81efc4"
 },
  "managed_frames" : [
 {
    "native_address" : "unregistered"
  }
,
 {
    "is_managed" : "true",
    "guid" : "6649516E-5B35-4231-9FB2-62B421AF0ADB",
    "token" : "0x00000",
    "native_offset" : "0x0",
    "filename" : "mscorlib.dll",
    "sizeofimage" : "0x450000",
    "timestamp" : "0xa2bd1ab9",
    "il_offset" : "0x0000b"
  }
,
 {
    "is_managed" : "true",
    "guid" : "6649516E-5B35-4231-9FB2-62B421AF0ADB",
    "token" : "0x6001e7c",
    "native_offset" : "0x0",
    "filename" : "mscorlib.dll",
    "sizeofimage" : "0x450000",
    "timestamp" : "0xa2bd1ab9",
    "il_offset" : "0x00019"
  }
,
 {
    "is_managed" : "true",
    "guid" : "7BB62E53-530F-48D5-9590-F3BFFAC96041",
    "token" : "0x600006b",
    "native_offset" : "0x0",
    "filename" : "reserve",
    "sizeofimage" : "0xe000",
    "timestamp" : "0x5d5169f2",
    "il_offset" : "0x0018d"
  }
,
 {
    "is_managed" : "true",
    "guid" : "7BB62E53-530F-48D5-9590-F3BFFAC96041",
    "token" : "0x6000057",
    "native_offset" : "0x0",
    "filename" : "reserve",
    "sizeofimage" : "0xe000",
    "timestamp" : "0x5d5169f2",
    "il_offset" : "0x00000"
  }
,
 {
    "is_managed" : "true",
    "guid" : "6649516E-5B35-4231-9FB2-62B421AF0ADB",
    "token" : "0x6001e55",
    "native_offset" : "0x0",
    "filename" : "mscorlib.dll",
    "sizeofimage" : "0x450000",
    "timestamp" : "0xa2bd1ab9",
    "il_offset" : "0x00014"
  }
,
 {
    "is_managed" : "true",
    "guid" : "6649516E-5B35-4231-9FB2-62B421AF0ADB",
    "token" : "0x6001e57",
    "native_offset" : "0x0",
    "filename" : "mscorlib.dll",
    "sizeofimage" : "0x450000",
    "timestamp" : "0xa2bd1ab9",
    "il_offset" : "0x00008"
  }
,
 {
    "is_managed" : "true",
    "guid" : "6649516E-5B35-4231-9FB2-62B421AF0ADB",
    "token" : "0x00000",
    "native_offset" : "0x0",
    "filename" : "mscorlib.dll",
    "sizeofimage" : "0x450000",
    "timestamp" : "0xa2bd1ab9",
    "il_offset" : "0x0001e"
  }

 ],
"unmanaged_frames" : [
{
  "native_address" : "unregistered"
 }
,
{
  "native_address" : "unregistered"
 }
,
{
  "native_address" : "unregistered"
 }
,
{
  "native_address" : "unregistered"
 }
,
{
  "native_address" : "unregistered"
 }
,
{
  "native_address" : "unregistered"
 }
,
{
  "native_address" : "unregistered"
 }
,
{
  "native_address" : "unregistered"
 }
,
{
  "native_address" : "unregistered"
 }
,
{
  "native_address" : "unregistered"
 }

]
},
{
"is_managed" : false,
"offset_free_hash" : "0x0",
"offset_rich_hash" : "0x0",
"crashed" : false,
"native_thread_id" : "0x7f021c6a7700",
"thread_info_addr" : "0x7f0214000b20",
"thread_name" : "Finalizer",
"ctx" : {
  "IP" : "0x7f021d7f3086",
  "SP" : "0x7f021c6a6c80",
  "BP" : "0x55d22b80f6a0"
},
"unmanaged_frames" : [
{
  "native_address" : "unregistered"
 }
,
{
  "native_address" : "unregistered"
 }
,
{
  "native_address" : "unregistered"
 }
,
{
  "native_address" : "unregistered"
 }
,
{
  "native_address" : "unregistered"
 }
,
{
  "native_address" : "unregistered"
 }
,
{
  "native_address" : "unregistered"
 }
,
{
  "native_address" : "unregistered"
 }
,
{
  "native_address" : "unregistered"
 }
,
{
  "native_address" : "unregistered"
 }
,
{
  "native_address" : "unregistered"
 }

]
}
]
}